vzug/__init__.py
vzug/constants.py
vzug/vzug.py
python_vzug-0.2.4.dist-info/LICENSE
python_vzug-0.2.4.dist-info/METADATA
python_vzug-0.2.4.dist-info/WHEEL
python_vzug-0.2.4.dist-info/top_level.txt
python_vzug-0.2.4.dist-info/zip-safe
python_vzug-0.2.4.dist-info/RECORD
