Metadata-Version: 2.1
Name: python-vzug
Version: 0.2.4
Summary: Python API for V-ZUG devices
Home-page: https://github.com/MoritzBuetzer/python-vzug
Author: Moritz Bützer
Author-email: moritz@buetzer.bz
License: Apache License 2.0
Platform: UNKNOWN
Classifier: Development Status :: 3 - Alpha
Classifier: Environment :: Console
Classifier: Intended Audience :: Developers
Classifier: License :: OSI Approved :: Apache Software License
Classifier: Operating System :: MacOS :: MacOS X
Classifier: Operating System :: Microsoft :: Windows
Classifier: Operating System :: POSIX
Classifier: Operating System :: Unix
Classifier: Programming Language :: Python :: 3.7
Classifier: Programming Language :: Python :: 3.8
Classifier: Topic :: Utilities
Requires-Dist: requests
Requires-Dist: yarl
